Metadata-Version: 2.1
Name: auditee
Version: 0.0.1.dev2
Summary: auditee
Home-page: https://github.com/sbellem/auditee
Author: Sylvain Bellemare
License: UNKNOWN
Project-URL: Source, https://github.com/sbellem/auditee
Project-URL: Tracker, https://github.com/sbellem/auditee/issues
Platform: linux
Classifier: Development Status :: 1 - Planning
Classifier: Intended Audience :: Developers
Classifier: License :: OSI Approved :: GNU General Public License v3 (GPLv3)
Classifier: Operating System :: POSIX
Classifier: Programming Language :: Python :: 3
Classifier: Programming Language :: Python :: 3 :: Only
Classifier: Programming Language :: Python :: 3.8
Classifier: Programming Language :: Python :: 3.9
Classifier: Topic :: Utilities
Requires-Python: >=3.6
Provides-Extra: dev
Provides-Extra: docs
Provides-Extra: test
